README.rst
setup.py
micropython_umqtt.simple.egg-info/PKG-INFO
micropython_umqtt.simple.egg-info/SOURCES.txt
micropython_umqtt.simple.egg-info/dependency_links.txt
micropython_umqtt.simple.egg-info/top_level.txt
umqtt/simple.py