Metadata-Version: 1.0
Name: micropython-umqtt.simple
Version: 1.1
Summary: Lightweight MQTT client for MicroPython.
Home-page: https://github.com/micropython/micropython/issues/405
Author: MicroPython Developers
Author-email: micro-python@googlegroups.com
License: MIT
Platform: UNKNOWN
